pyxlmapper/__about__.py
pyxlmapper/__init__.py
pyxlmapper/__main__.py
pyxlmapper/formatters.py
pyxlmapper/mapper.py
pyxlmapper/util.py
pyxlmapper-0.0.2.4.dist-info/METADATA
pyxlmapper-0.0.2.4.dist-info/WHEEL
pyxlmapper-0.0.2.4.dist-info/RECORD
