Metadata-Version: 2.4
Name: pyxlmapper
Version: 0.0.2.4
Summary: Mapper and parser for hierarchical spreadsheets
Author-email: Ruslan Panasiuk <ruslan.panasiuk@gmail.com>
Requires-Python: >=3.8
Requires-Dist: openpyxl>=3.1.5
Provides-Extra: dev
Requires-Dist: black; extra == 'dev'
Requires-Dist: hatch; extra == 'dev'
Requires-Dist: mypy; extra == 'dev'
Requires-Dist: pre-commit; extra == 'dev'
Requires-Dist: pytest>=7.0; extra == 'dev'
Provides-Extra: docs
